llama_index/llms/everlyai/__init__.py
llama_index/llms/everlyai/base.py
llama_index/llms/everlyai/utils.py
llama_index_llms_everlyai-0.4.2.dist-info/METADATA
llama_index_llms_everlyai-0.4.2.dist-info/WHEEL
llama_index_llms_everlyai-0.4.2.dist-info/licenses/LICENSE
llama_index_llms_everlyai-0.4.2.dist-info/RECORD
